{
  "gate": "A",
  "objective": "O2",
  "sae_release": "gemma-scope-2-270m-it-res",
  "sae_id": "layer_12_width_16k_l0_medium",
  "expect_d_in": 640,
  "expect_layer": 12,
  "cfg_pinned": {
    "d_in": 640,
    "d_sae": 16384,
    "hook_name": "blocks.12.hook_resid_post",
    "hook_layer": null,
    "dtype": "float32",
    "normalize_activations": "none",
    "apply_b_dec_to_input": false,
    "prepend_bos": true,
    "model_name": "google/gemma-3-270m-it"
  },
  "weight_shapes": {
    "W_enc": [
      640,
      16384
    ],
    "W_dec": [
      16384,
      640
    ]
  },
  "cfg_full": {
    "d_in": 640,
    "d_sae": 16384,
    "dtype": "float32",
    "device": "cpu",
    "apply_b_dec_to_input": false,
    "normalize_activations": "none",
    "reshape_activations": "none",
    "metadata": "SAEMetadata({'sae_lens_version': '6.44.2', 'sae_lens_training_version': None, 'model_name': 'google/gemma-3-270m-it', 'hook_name': 'blocks.12.hook_resid_post', 'hook_head_index': None, 'prepend_bos': True, 'dataset_path': 'monology/pile-uncopyrighted', 'context_size': 1024, 'hf_hook_name': 'model.layers.12.output', 'neuronpedia_id': 'gemma-3-270m-it/12-gemmascope-2-res-16k'})"
  },
  "cfg_metadata_full": {
    "sae_lens_version": "6.44.2",
    "sae_lens_training_version": null,
    "model_name": "google/gemma-3-270m-it",
    "hook_name": "blocks.12.hook_resid_post",
    "hook_head_index": null,
    "prepend_bos": true,
    "dataset_path": "monology/pile-uncopyrighted",
    "context_size": 1024,
    "hf_hook_name": "model.layers.12.output",
    "neuronpedia_id": "gemma-3-270m-it/12-gemmascope-2-res-16k"
  },
  "env": {
    "sae_lens": "6.44.2",
    "torch": "2.7.1"
  }
}